README.md
setup.cfg
setup.py
qfilter/__init__.py
qfilter.egg-info/PKG-INFO
qfilter.egg-info/SOURCES.txt
qfilter.egg-info/dependency_links.txt
qfilter.egg-info/not-zip-safe
qfilter.egg-info/top_level.txt