Metadata-Version: 1.0
Name: qfilter
Version: 0.3
Summary: Simple querystring filter
Home-page: https://github.com/rvettori/qfilter
Author: Rafael Vettori
Author-email: rafael.vettori@gmail.com
License: MIT
Platform: UNKNOWN
